{"trial_id": "01", "hyperparameters": {"space": [{"class_name": "Int", "config": {"name": "num_layers", "default": null, "conditions": [], "min_value": 2, "max_value": 20, "step": 1, "sampling": "linear"}}, {"class_name": "Int", "config": {"name": "units_0", "default": null, "conditions": [], "min_value": 32, "max_value": 512, "step": 32, "sampling": "linear"}}, {"class_name": "Int", "config": {"name": "units_1", "default": null, "conditions": [], "min_value": 32, "max_value": 512, "step": 32, "sampling": "linear"}}, {"class_name": "Choice", "config": {"name": "learning_rate", "default": 0.01, "conditions": [], "values": [0.01, 0.001, 0.0001], "ordered": true}}, {"class_name": "Int", "config": {"name": "units_2", "default": null, "conditions": [], "min_value": 32, "max_value": 512, "step": 32, "sampling": "linear"}}, {"class_name": "Int", "config": {"name": "units_3", "default": null, "conditions": [], "min_value": 32, "max_value": 512, "step": 32, "sampling": "linear"}}, {"class_name": "Int", "config": {"name": "units_4", "default": null, "conditions": [], "min_value": 32, "max_value": 512, "step": 32, "sampling": "linear"}}, {"class_name": "Int", "config": {"name": "units_5", "default": null, "conditions": [], "min_value": 32, "max_value": 512, "step": 32, "sampling": "linear"}}, {"class_name": "Int", "config": {"name": "units_6", "default": null, "conditions": [], "min_value": 32, "max_value": 512, "step": 32, "sampling": "linear"}}, {"class_name": "Int", "config": {"name": "units_7", "default": null, "conditions": [], "min_value": 32, "max_value": 512, "step": 32, "sampling": "linear"}}], "values": {"num_layers": 8, "units_0": 96, "units_1": 224, "learning_rate": 0.0001, "units_2": 32, "units_3": 160, "units_4": 352, "units_5": 192, "units_6": 128, "units_7": 32}}, "metrics": {"metrics": {"accuracy": {"direction": "max", "observations": [{"value": [0.7947883009910583], "step": 7}]}, "loss": {"direction": "min", "observations": [{"value": [0.4445742666721344], "step": 7}]}, "val_accuracy": {"direction": "max", "observations": [{"value": [0.7857142686843872], "step": 7}]}, "val_loss": {"direction": "min", "observations": [{"value": [0.448137104511261], "step": 7}]}}}, "score": 0.7857142686843872, "best_step": 7, "status": "COMPLETED", "message": null}